README.txt
scopeformatter.py
setup.cfg
setup.py
ScopeFormatter.egg-info/PKG-INFO
ScopeFormatter.egg-info/SOURCES.txt
ScopeFormatter.egg-info/dependency_links.txt
ScopeFormatter.egg-info/top_level.txt