Metadata-Version: 1.0
Name: ScopeFormatter
Version: 1.0.1
Summary: Format a string using names in the current scope.
Home-page: http://pypi.python.org/pypi/ScopeFormatter
Author: Luke Stebbing
Author-email: luke@lukestebbing.com
License: MIT
Platform: UNKNOWN
Classifier: Development Status :: 5 - Production/Stable
Classifier: Intended Audience :: Developers
Classifier: License :: OSI Approved :: MIT License
Classifier: Programming Language :: Python :: 2.6
Classifier: Programming Language :: Python :: 3
Classifier: Operating System :: OS Independent
